bucket_gcp/__init__.py
bucket_gcp/admin.py
bucket_gcp/apps.py
bucket_gcp/gcpbucket.py
bucket_gcp/models.py
bucket_gcp/tests.py
bucket_gcp/views.py
bucket_gcp/migrations/__init__.py
gcpbucket/__init__.py
gcpbucket/settings.py
gcpbucket/urls.py
gcpbucket/wsgi.py
bucket_gcp-1.2.dist-info/LICENSE
bucket_gcp-1.2.dist-info/METADATA
bucket_gcp-1.2.dist-info/WHEEL
bucket_gcp-1.2.dist-info/top_level.txt
bucket_gcp-1.2.dist-info/RECORD
